<?xml version="1.0" encoding="UTF-8"?>
<SDTNotasExport xmlns="NFe"><CpfCnpj>00519547000106</CpfCnpj><DtIni>04/10/2022</DtIni><DtFin>04/10/2022</DtFin><TipoArq>4</TipoArq><Versao/><Reg20><Reg20Item><TipoNf>RPS</TipoNf><NumNf>970</NumNf><SerNf>001</SerNf><DtEmiNf>04/10/2022</DtEmiNf><DtHrGerNf>NAO</DtHrGerNf><CodVernf>14.01</CodVernf><NumRps>0</NumRps><SerRps>8230</SerRps><DtEmiRps>0,00</DtEmiRps><TipoCpfCnpjPre>F</TipoCpfCnpjPre><CpfCnpjPre>82.30,.00/-</CpfCnpjPre><RazSocPre>4,35</RazSocPre><LogPre>358,00</LogPre><NumEndPre>0,00</NumEndPre><ComplEndPre>40181203000308</ComplEndPre><BairroPre>ABC SISTEMA DE TRANSPORTE SPE S.A</BairroPre><MunPre/><SiglaUFPre>RUA JOAQUIM CASEMIRO, GARAGE 1</SiglaUFPre><CepPre>290</CepPre><EmailPre/><TipoTribPre>PLANALTO</TipoTribPre><DtAdeSN>SÃO BERNARDO DO CAMPO</DtAdeSN><AlqIssSN>SP</AlqIssSN><SitNf>09890050</SitNf><DataCncNf/><MotivoCncNf/><TipoCpfCnpjTom>F</TipoCpfCnpjTom><CpfCnpjTom>RU.A J.OAQ/UIM -CA</CpfCnpjTom><RazSocTom>290</RazSocTom><LogTom/><NumEndTom>PLANALTO</NumEndTom><ComplEndTom>SÃO BERNARDO DO CAMPO</ComplEndTom><BairroTom>SP</BairroTom><MunTom>09890050</MunTom><SiglaUFTom>dantas@flexibus.com.br</SiglaUFTom><CepTom/><EMailTom/><LogLocPre>
</LogLocPre><NumEndLocPre/><ComplEndLocPre/><BairroLocPre/><MunLocPre/><SiglaUFLocpre/><CepLocPre/><CodSrv/><DiscrSrv/><VlNFS/><VlDed/><DiscrDed/><VlBasCalc/><AlqIss/><VlIss/><VlIssRet/><Reg30/></Reg20Item></Reg20><Reg90><QtdRegNormal>1</QtdRegNormal><ValorNFS>8230.00</ValorNFS><ValorISS>358.00</ValorISS><ValorDed>0.00</ValorDed><ValorIssRet>0.00</ValorIssRet><QtdReg30>0</QtdReg30><ValorTributos>0.00</ValorTributos></Reg90>
</SDTNotasExport>
